{"v":"5.7.4","fr":20,"ip":0,"op":120,"w":800,"h":1200,"nm":"inbox","ddd":0,"assets":[],"layers":[{"ddd":0,"ind":1,"ty":4,"nm":"Message1/Inbox contornos 3","sr":1,"ks":{"o":{"a":0,"k":100,"ix":11},"r":{"a":1,"k":[{"i":{"x":[0.35],"y":[1]},"o":{"x":[0.333],"y":[0]},"t":92.001,"s":[0]},{"t":116.000706256893,"s":[45]}],"ix":10},"p":{"a":1,"k":[{"i":{"x":0.667,"y":1},"o":{"x":0.333,"y":0},"t":90.001,"s":[298,459.99999999999994,0],"to":[0,0,0],"ti":[-59.443,75.508,0]},{"t":114.000694781204,"s":[408,1026,0]}],"ix":2,"l":2},"a":{"a":0,"k":[19,210,0],"ix":1,"l":2},"s":{"a":1,"k":[{"i":{"x":[0.495,0.495,0.667],"y":[1,1,1]},"o":{"x":[0.562,0.562,0.333],"y":[0,0,0]},"t":92.001,"s":[100,100,100]},{"t":116.000706256893,"s":[0,0,100]}],"ix":6,"l":2}},"ao":0,"shapes":[{"ty":"gr","it":[{"ind":0,"ty":"sh","ix":1,"ks":{"a":0,"k":{"i":[[2.13,-4.474],[0,0],[0,0],[3.899,3.039],[4.932,0.335],[0,0],[4.264,-2.522]],"o":[[0,0],[0,0],[-1.53,-4.701],[-3.9,-3.04],[0,0],[-4.946,-0.289],[-4.265,2.522]],"v":[[-212.914,-68.129],[65.995,82.329],[212.914,-39.942],[204.585,-51.818],[191.034,-56.996],[-188.974,-82.287],[-203.104,-78.861]],"c":true},"ix":2},"nm":"Trazado 1","mn":"ADBE Vector Shape - Group","hd":false},{"ty":"fl","c":{"a":0,"k":[1,1,1,1],"ix":4},"o":{"a":0,"k":30,"ix":5},"r":1,"bm":0,"nm":"Relleno 1","mn":"ADBE Vector Graphic - Fill","hd":false},{"ty":"tr","p":{"a":0,"k":[227.103,82.826],"ix":2},"a":{"a":0,"k":[0,0],"ix":1},"s":{"a":0,"k":[100,100],"ix":3},"r":{"a":0,"k":0,"ix":6},"o":{"a":0,"k":100,"ix":7},"sk":{"a":0,"k":0,"ix":4},"sa":{"a":0,"k":0,"ix":5},"nm":"Transformar"}],"nm":"Grupo 1","np":4,"cix":2,"bm":0,"ix":1,"mn":"ADBE Vector Group","hd":false},{"ty":"gr","it":[{"ind":0,"ty":"sh","ix":1,"ks":{"a":0,"k":{"i":[[2.13,-4.474],[0,0],[0,0],[3.899,3.039],[4.932,0.335],[0,0],[4.264,-2.522]],"o":[[0,0],[0,0],[-1.53,-4.701],[-3.9,-3.04],[0,0],[-4.946,-0.289],[-4.265,2.522]],"v":[[-212.914,-68.006],[65.995,82.452],[212.914,-39.819],[204.585,-51.694],[191.034,-56.872],[-188.974,-82.163],[-203.104,-78.738]],"c":true},"ix":2},"nm":"Trazado 1","mn":"ADBE Vector Shape - Group","hd":false},{"ty":"fl","c":{"a":0,"k":[0.2901960784313726,0.5647058823529412,0.8862745098039215,1],"ix":4},"o":{"a":0,"k":100,"ix":5},"r":1,"bm":0,"nm":"Relleno 1","mn":"ADBE Vector Graphic - Fill","hd":false},{"ty":"tr","p":{"a":0,"k":[227.103,82.703],"ix":2},"a":{"a":0,"k":[0,0],"ix":1},"s":{"a":0,"k":[100,100],"ix":3},"r":{"a":0,"k":0,"ix":6},"o":{"a":0,"k":100,"ix":7},"sk":{"a":0,"k":0,"ix":4},"sa":{"a":0,"k":0,"ix":5},"nm":"Transformar"}],"nm":"Grupo 2","np":4,"cix":2,"bm":0,"ix":2,"mn":"ADBE Vector Group","hd":false},{"ty":"gr","it":[{"ind":0,"ty":"sh","ix":1,"ks":{"a":0,"k":{"i":[[2.158,-4.437],[0,0],[0,0],[3.899,3.039],[4.932,0.335],[0,0],[4.262,-2.486]],"o":[[0,0],[0,0],[-1.53,-4.701],[-3.9,-3.039],[0,0],[-4.925,-0.306],[-4.262,2.486]],"v":[[-212.914,-83.539],[2.993,97.552],[212.914,-55.159],[204.585,-67.036],[191.034,-72.213],[-188.974,-97.504],[-203.066,-94.159]],"c":true},"ix":2},"nm":"Trazado 1","mn":"ADBE Vector Shape - Group","hd":false},{"ty":"fl","c":{"a":0,"k":[0.2901960784313726,0.5647058823529412,0.8862745098039215,1],"ix":4},"o":{"a":0,"k":100,"ix":5},"r":1,"bm":0,"nm":"Relleno 1","mn":"ADBE Vector Graphic - Fill","hd":false},{"ty":"tr","p":{"a":0,"k":[227.103,98.235],"ix":2},"a":{"a":0,"k":[0,0],"ix":1},"s":{"a":0,"k":[100,100],"ix":3},"r":{"a":0,"k":0,"ix":6},"o":{"a":0,"k":100,"ix":7},"sk":{"a":0,"k":0,"ix":4},"sa":{"a":0,"k":0,"ix":5},"nm":"Transformar"}],"nm":"Grupo 3","np":4,"cix":2,"bm":0,"ix":3,"mn":"ADBE Vector Group","hd":false},{"ty":"gr","it":[{"ind":0,"ty":"sh","ix":1,"ks":{"a":0,"k":{"i":[[0.222,-3.043],[0,0],[-4.317,-4.944],[-6.547,-0.463],[0,0],[-4.944,4.317],[-0.462,6.547],[0,0],[4.324,4.938],[6.546,0.479],[0,0],[4.262,-2.486],[2.158,-4.437]],"o":[[0,0],[-0.425,6.549],[4.317,4.944],[0,0],[6.549,0.424],[4.944,-4.316],[0,0],[0.391,-6.551],[-4.324,-4.938],[0,0],[-4.925,-0.305],[-4.262,2.486],[-1.35,2.737]],"v":[[-209.132,-98.199],[-220.265,69.121],[-214.188,87.065],[-197.227,95.506],[182.782,120.797],[200.726,114.719],[209.166,97.758],[220.299,-69.24],[214.16,-87.171],[197.197,-95.625],[-182.811,-120.916],[-196.903,-117.571],[-206.751,-106.951]],"c":true},"ix":2},"nm":"Trazado 1","mn":"ADBE Vector Shape - Group","hd":false},{"ty":"fl","c":{"a":0,"k":[0.2901960784313726,0.5647058823529412,0.8862745098039215,1],"ix":4},"o":{"a":0,"k":100,"ix":5},"r":1,"bm":0,"nm":"Relleno 1","mn":"ADBE Vector Graphic - Fill","hd":false},{"ty":"tr","p":{"a":0,"k":[220.94,121.969],"ix":2},"a":{"a":0,"k":[0,0],"ix":1},"s":{"a":0,"k":[100,100],"ix":3},"r":{"a":0,"k":0,"ix":6},"o":{"a":0,"k":100,"ix":7},"sk":{"a":0,"k":0,"ix":4},"sa":{"a":0,"k":0,"ix":5},"nm":"Transformar"}],"nm":"Grupo 4","np":4,"cix":2,"bm":0,"ix":4,"mn":"ADBE Vector Group","hd":false}],"ip":92.0105482725471,"op":121.010714670045,"st":83.0205170227726,"bm":0},{"ddd":0,"ind":2,"ty":4,"nm":"Message2/Inbox contornos 3","sr":1,"ks":{"o":{"a":0,"k":100,"ix":11},"r":{"a":1,"k":[{"i":{"x":[0.43],"y":[1]},"o":{"x":[0.33],"y":[0]},"t":92.001,"s":[0]},{"t":110.000671829824,"s":[45]}],"ix":10},"p":{"a":1,"k":[{"i":{"x":0.667,"y":1},"o":{"x":0.333,"y":0},"t":92.001,"s":[206,762,0],"to":[0,0,0],"ti":[-16.636,53.473,0]},{"t":110.000671829824,"s":[405.99999999999994,1032,0]}],"ix":2,"l":2},"a":{"a":0,"k":[65,333,0],"ix":1,"l":2},"s":{"a":1,"k":[{"i":{"x":[0.523,0.523,0.667],"y":[1,1,1]},"o":{"x":[0.641,0.641,0.333],"y":[0,0,0]},"t":92.001,"s":[100,100,100]},{"t":110.000671829824,"s":[0,0,100]}],"ix":6,"l":2}},"ao":0,"shapes":[{"ty":"gr","it":[{"ind":0,"ty":"sh","ix":1,"ks":{"a":0,"k":{"i":[[0.838,-5.521],[0,0],[0,0],[5.192,1.937],[5.39,-1.292],[0,0],[3.784,-4.106]],"o":[[0,0],[0,0],[-3.225,-4.507],[-5.192,-1.937],[0,0],[-5.433,1.285],[-3.784,4.105]],"v":[[-232.831,14.059],[63.196,110.589],[232.831,-98.946],[219.915,-108.832],[203.679,-109.822],[-211.595,-8.98],[-225.738,-0.71]],"c":true},"ix":2},"nm":"Trazado 1","mn":"ADBE Vector Shape - Group","hd":false},{"ty":"fl","c":{"a":0,"k":[1,1,1,1],"ix":4},"o":{"a":0,"k":15,"ix":5},"r":1,"bm":0,"nm":"Relleno 1","mn":"ADBE Vector Graphic - Fill","hd":false},{"ty":"tr","p":{"a":0,"k":[233.614,111.621],"ix":2},"a":{"a":0,"k":[0,0],"ix":1},"s":{"a":0,"k":[100,100],"ix":3},"r":{"a":0,"k":0,"ix":6},"o":{"a":0,"k":100,"ix":7},"sk":{"a":0,"k":0,"ix":4},"sa":{"a":0,"k":0,"ix":5},"nm":"Transformar"}],"nm":"Grupo 1","np":4,"cix":2,"bm":0,"ix":1,"mn":"ADBE Vector Group","hd":false},{"ty":"gr","it":[{"ind":0,"ty":"sh","ix":1,"ks":{"a":0,"k":{"i":[[0.838,-5.521],[0,0],[0,0],[5.192,1.937],[5.39,-1.292],[0,0],[3.784,-4.106]],"o":[[0,0],[0,0],[-3.225,-4.507],[-5.192,-1.937],[0,0],[-5.433,1.285],[-3.784,4.105]],"v":[[-232.831,14.321],[63.196,110.851],[232.831,-98.683],[219.915,-108.57],[203.679,-109.559],[-211.595,-8.717],[-225.738,-0.447]],"c":true},"ix":2},"nm":"Trazado 1","mn":"ADBE Vector Shape - Group","hd":false},{"ty":"fl","c":{"a":0,"k":[0.2901960784313726,0.5647058823529412,0.8862745098039215,1],"ix":4},"o":{"a":0,"k":100,"ix":5},"r":1,"bm":0,"nm":"Relleno 1","mn":"ADBE Vector Graphic - Fill","hd":false},{"ty":"tr","p":{"a":0,"k":[233.614,111.359],"ix":2},"a":{"a":0,"k":[0,0],"ix":1},"s":{"a":0,"k":[100,100],"ix":3},"r":{"a":0,"k":0,"ix":6},"o":{"a":0,"k":100,"ix":7},"sk":{"a":0,"k":0,"ix":4},"sa":{"a":0,"k":0,"ix":5},"nm":"Transformar"}],"nm":"Grupo 2","np":4,"cix":2,"bm":0,"ix":2,"mn":"ADBE Vector Group","hd":false},{"ty":"gr","it":[{"ind":0,"ty":"sh","ix":1,"ks":{"a":0,"k":{"i":[[0.838,-5.521],[0,0],[0,0],[5.192,1.937],[5.39,-1.292],[0,0],[3.784,-4.106]],"o":[[0,0],[0,0],[-3.227,-4.507],[-5.193,-1.938],[0,0],[-5.433,1.284],[-3.784,4.105]],"v":[[-232.895,1.864],[59.528,123.042],[232.895,-111.399],[219.98,-121.284],[203.744,-122.275],[-211.659,-21.175],[-225.802,-12.905]],"c":true},"ix":2},"nm":"Trazado 1","mn":"ADBE Vector Shape - Group","hd":false},{"ty":"fl","c":{"a":0,"k":[0.2901960784313726,0.5647058823529412,0.8862745098039215,1],"ix":4},"o":{"a":0,"k":100,"ix":5},"r":1,"bm":0,"nm":"Relleno 1","mn":"ADBE Vector Graphic - Fill","hd":false},{"ty":"tr","p":{"a":0,"k":[233.679,123.816],"ix":2},"a":{"a":0,"k":[0,0],"ix":1},"s":{"a":0,"k":[100,100],"ix":3},"r":{"a":0,"k":0,"ix":6},"o":{"a":0,"k":100,"ix":7},"sk":{"a":0,"k":0,"ix":4},"sa":{"a":0,"k":0,"ix":5},"nm":"Transformar"}],"nm":"Grupo 3","np":4,"cix":2,"bm":0,"ix":3,"mn":"ADBE Vector Group","hd":false},{"ty":"gr","it":[{"ind":0,"ty":"sh","ix":1,"ks":{"a":0,"k":{"i":[[-0.873,-3.448],[0,0],[-6.299,-3.826],[-7.159,1.747],[0,0],[-3.833,6.292],[1.71,7.166],[0,0],[2.066,2.891],[5.193,1.937],[5.391,-1.292],[0,0],[3.785,-4.105],[0.839,-5.52]],"o":[[0,0],[1.752,7.158],[6.299,3.825],[0,0],[7.153,-1.769],[3.833,-6.292],[0,0],[-0.869,-3.445],[-3.225,-4.507],[-5.193,-1.938],[0,0],[-5.434,1.283],[-3.784,4.105],[-0.533,3.517]],"v":[[-257.391,-34.432],[-212.987,148.268],[-200.413,165.422],[-179.395,168.668],[236.264,67.569],[253.415,54.986],[256.729,33.976],[212.326,-148.66],[207.884,-158.248],[194.968,-168.133],[178.733,-169.123],[-236.669,-68.024],[-250.813,-59.755],[-257.906,-44.985]],"c":true},"ix":2},"nm":"Trazado 1","mn":"ADBE Vector Shape - Group","hd":false},{"ty":"fl","c":{"a":0,"k":[0.2901960784313726,0.5647058823529412,0.8862745098039215,1],"ix":4},"o":{"a":0,"k":100,"ix":5},"r":1,"bm":0,"nm":"Relleno 1","mn":"ADBE Vector Graphic - Fill","hd":false},{"ty":"tr","p":{"a":0,"k":[258.689,170.666],"ix":2},"a":{"a":0,"k":[0,0],"ix":1},"s":{"a":0,"k":[100,100],"ix":3},"r":{"a":0,"k":0,"ix":6},"o":{"a":0,"k":100,"ix":7},"sk":{"a":0,"k":0,"ix":4},"sa":{"a":0,"k":0,"ix":5},"nm":"Transformar"}],"nm":"Grupo 4","np":4,"cix":2,"bm":0,"ix":4,"mn":"ADBE Vector Group","hd":false}],"ip":92.0105482725471,"op":121.010714670045,"st":91.0205629255308,"bm":0},{"ddd":0,"ind":3,"ty":4,"nm":"Message1/Inbox contornos","sr":1,"ks":{"o":{"a":0,"k":100,"ix":11},"r":{"a":1,"k":[{"i":{"x":[0.667],"y":[1]},"o":{"x":[0.659],"y":[0]},"t":4,"s":[45]},{"i":{"x":[0.833],"y":[0.833]},"o":{"x":[0.167],"y":[0.167]},"t":41,"s":[0]},{"i":{"x":[0.318],"y":[1]},"o":{"x":[0.657],"y":[0]},"t":59,"s":[0]},{"t":93.0005336195634,"s":[720]}],"ix":10},"p":{"a":1,"k":[{"i":{"x":0.667,"y":1},"o":{"x":0.333,"y":0},"t":4,"s":[408,1026,0],"to":[61.667,-78.333,0],"ti":[0,0,0]},{"i":{"x":0.833,"y":0.833},"o":{"x":0.167,"y":0.167},"t":41,"s":[298,459.99999999999994,0],"to":[0,0,0],"ti":[0,0,0]},{"i":{"x":0.833,"y":0.833},"o":{"x":0.167,"y":0.167},"t":55,"s":[298,459.99999999999994,0],"to":[0,0,0],"ti":[0,0,0]},{"t":59.0003385328413,"s":[508,368,0]}],"ix":2,"l":2},"a":{"a":1,"k":[{"i":{"x":0.833,"y":0.833},"o":{"x":0.167,"y":0.167},"t":55,"s":[19,210,0],"to":[35,-15.333,0],"ti":[-35,15.333,0]},{"t":59.0003385328413,"s":[229,118,0]}],"ix":1,"l":2},"s":{"a":1,"k":[{"i":{"x":[0.36,0.36,0.667],"y":[1,1,1]},"o":{"x":[0.635,0.635,0.333],"y":[0,0,0]},"t":4,"s":[0,0,100]},{"t":41.0002352516355,"s":[100,100,100]}],"ix":6,"l":2}},"ao":0,"shapes":[{"ty":"gr","it":[{"ind":0,"ty":"sh","ix":1,"ks":{"a":0,"k":{"i":[[2.13,-4.474],[0,0],[0,0],[3.899,3.039],[4.932,0.335],[0,0],[4.264,-2.522]],"o":[[0,0],[0,0],[-1.53,-4.701],[-3.9,-3.04],[0,0],[-4.946,-0.289],[-4.265,2.522]],"v":[[-212.914,-68.129],[65.995,82.329],[212.914,-39.942],[204.585,-51.818],[191.034,-56.996],[-188.974,-82.287],[-203.104,-78.861]],"c":true},"ix":2},"nm":"Trazado 1","mn":"ADBE Vector Shape - Group","hd":false},{"ty":"fl","c":{"a":0,"k":[1,1,1,1],"ix":4},"o":{"a":0,"k":30,"ix":5},"r":1,"bm":0,"nm":"Relleno 1","mn":"ADBE Vector Graphic - Fill","hd":false},{"ty":"tr","p":{"a":0,"k":[227.103,82.826],"ix":2},"a":{"a":0,"k":[0,0],"ix":1},"s":{"a":0,"k":[100,100],"ix":3},"r":{"a":0,"k":0,"ix":6},"o":{"a":0,"k":100,"ix":7},"sk":{"a":0,"k":0,"ix":4},"sa":{"a":0,"k":0,"ix":5},"nm":"Transformar"}],"nm":"Grupo 1","np":4,"cix":2,"bm":0,"ix":1,"mn":"ADBE Vector Group","hd":false},{"ty":"gr","it":[{"ind":0,"ty":"sh","ix":1,"ks":{"a":0,"k":{"i":[[2.13,-4.474],[0,0],[0,0],[3.899,3.039],[4.932,0.335],[0,0],[4.264,-2.522]],"o":[[0,0],[0,0],[-1.53,-4.701],[-3.9,-3.04],[0,0],[-4.946,-0.289],[-4.265,2.522]],"v":[[-212.914,-68.006],[65.995,82.452],[212.914,-39.819],[204.585,-51.694],[191.034,-56.872],[-188.974,-82.163],[-203.104,-78.738]],"c":true},"ix":2},"nm":"Trazado 1","mn":"ADBE Vector Shape - Group","hd":false},{"ty":"fl","c":{"a":0,"k":[0.2901960784313726,0.5647058823529412,0.8862745098039215,1],"ix":4},"o":{"a":0,"k":100,"ix":5},"r":1,"bm":0,"nm":"Relleno 1","mn":"ADBE Vector Graphic - Fill","hd":false},{"ty":"tr","p":{"a":0,"k":[227.103,82.703],"ix":2},"a":{"a":0,"k":[0,0],"ix":1},"s":{"a":0,"k":[100,100],"ix":3},"r":{"a":0,"k":0,"ix":6},"o":{"a":0,"k":100,"ix":7},"sk":{"a":0,"k":0,"ix":4},"sa":{"a":0,"k":0,"ix":5},"nm":"Transformar"}],"nm":"Grupo 2","np":4,"cix":2,"bm":0,"ix":2,"mn":"ADBE Vector Group","hd":false},{"ty":"gr","it":[{"ind":0,"ty":"sh","ix":1,"ks":{"a":0,"k":{"i":[[2.158,-4.437],[0,0],[0,0],[3.899,3.039],[4.932,0.335],[0,0],[4.262,-2.486]],"o":[[0,0],[0,0],[-1.53,-4.701],[-3.9,-3.039],[0,0],[-4.925,-0.306],[-4.262,2.486]],"v":[[-212.914,-83.539],[2.993,97.552],[212.914,-55.159],[204.585,-67.036],[191.034,-72.213],[-188.974,-97.504],[-203.066,-94.159]],"c":true},"ix":2},"nm":"Trazado 1","mn":"ADBE Vector Shape - Group","hd":false},{"ty":"fl","c":{"a":0,"k":[0.2901960784313726,0.5647058823529412,0.8862745098039215,1],"ix":4},"o":{"a":0,"k":100,"ix":5},"r":1,"bm":0,"nm":"Relleno 1","mn":"ADBE Vector Graphic - Fill","hd":false},{"ty":"tr","p":{"a":0,"k":[227.103,98.235],"ix":2},"a":{"a":0,"k":[0,0],"ix":1},"s":{"a":0,"k":[100,100],"ix":3},"r":{"a":0,"k":0,"ix":6},"o":{"a":0,"k":100,"ix":7},"sk":{"a":0,"k":0,"ix":4},"sa":{"a":0,"k":0,"ix":5},"nm":"Transformar"}],"nm":"Grupo 3","np":4,"cix":2,"bm":0,"ix":3,"mn":"ADBE Vector Group","hd":false},{"ty":"gr","it":[{"ind":0,"ty":"sh","ix":1,"ks":{"a":0,"k":{"i":[[0.222,-3.043],[0,0],[-4.317,-4.944],[-6.547,-0.463],[0,0],[-4.944,4.317],[-0.462,6.547],[0,0],[4.324,4.938],[6.546,0.479],[0,0],[4.262,-2.486],[2.158,-4.437]],"o":[[0,0],[-0.425,6.549],[4.317,4.944],[0,0],[6.549,0.424],[4.944,-4.316],[0,0],[0.391,-6.551],[-4.324,-4.938],[0,0],[-4.925,-0.305],[-4.262,2.486],[-1.35,2.737]],"v":[[-209.132,-98.199],[-220.265,69.121],[-214.188,87.065],[-197.227,95.506],[182.782,120.797],[200.726,114.719],[209.166,97.758],[220.299,-69.24],[214.16,-87.171],[197.197,-95.625],[-182.811,-120.916],[-196.903,-117.571],[-206.751,-106.951]],"c":true},"ix":2},"nm":"Trazado 1","mn":"ADBE Vector Shape - Group","hd":false},{"ty":"fl","c":{"a":0,"k":[0.2901960784313726,0.5647058823529412,0.8862745098039215,1],"ix":4},"o":{"a":0,"k":100,"ix":5},"r":1,"bm":0,"nm":"Relleno 1","mn":"ADBE Vector Graphic - Fill","hd":false},{"ty":"tr","p":{"a":0,"k":[220.94,121.969],"ix":2},"a":{"a":0,"k":[0,0],"ix":1},"s":{"a":0,"k":[100,100],"ix":3},"r":{"a":0,"k":0,"ix":6},"o":{"a":0,"k":100,"ix":7},"sk":{"a":0,"k":0,"ix":4},"sa":{"a":0,"k":0,"ix":5},"nm":"Transformar"}],"nm":"Grupo 4","np":4,"cix":2,"bm":0,"ix":4,"mn":"ADBE Vector Group","hd":false}],"ip":4.00002295137907,"op":93.0005336195634,"st":4.00002295137907,"bm":0},{"ddd":0,"ind":4,"ty":4,"nm":"Message2/Inbox contornos","sr":1,"ks":{"o":{"a":0,"k":100,"ix":11},"r":{"a":1,"k":[{"i":{"x":[0.667],"y":[1]},"o":{"x":[0.534],"y":[0]},"t":16,"s":[45]},{"i":{"x":[0.833],"y":[0.833]},"o":{"x":[0.167],"y":[0.167]},"t":41,"s":[0]},{"i":{"x":[0.318],"y":[1]},"o":{"x":[0.657],"y":[0]},"t":59,"s":[0]},{"t":93.0005336195634,"s":[720]}],"ix":10},"p":{"a":1,"k":[{"i":{"x":0.667,"y":1},"o":{"x":0.333,"y":0},"t":16,"s":[405.99999999999994,1032,0],"to":[32.667,-105,0],"ti":[0,0,0]},{"i":{"x":0.833,"y":0.833},"o":{"x":0.167,"y":0.167},"t":41,"s":[206,762,0],"to":[0,0,0],"ti":[0,0,0]},{"i":{"x":0.833,"y":0.833},"o":{"x":0.167,"y":0.167},"t":55,"s":[206,762,0],"to":[0,0,0],"ti":[0,0,0]},{"t":59.0003385328413,"s":[412,590,0]}],"ix":2,"l":2},"a":{"a":1,"k":[{"i":{"x":0.833,"y":0.833},"o":{"x":0.167,"y":0.167},"t":55,"s":[65,333,0],"to":[34.333,-28.667,0],"ti":[-34.333,28.667,0]},{"t":59.0003385328413,"s":[271,161,0]}],"ix":1,"l":2},"s":{"a":1,"k":[{"i":{"x":[0.254,0.254,0.667],"y":[1,1,1]},"o":{"x":[0.514,0.514,0.333],"y":[0,0,0]},"t":16,"s":[0,0,100]},{"t":41.0002352516355,"s":[100,100,100]}],"ix":6,"l":2}},"ao":0,"shapes":[{"ty":"gr","it":[{"ind":0,"ty":"sh","ix":1,"ks":{"a":0,"k":{"i":[[0.838,-5.521],[0,0],[0,0],[5.192,1.937],[5.39,-1.292],[0,0],[3.784,-4.106]],"o":[[0,0],[0,0],[-3.225,-4.507],[-5.192,-1.937],[0,0],[-5.433,1.285],[-3.784,4.105]],"v":[[-232.831,14.059],[63.196,110.589],[232.831,-98.946],[219.915,-108.832],[203.679,-109.822],[-211.595,-8.98],[-225.738,-0.71]],"c":true},"ix":2},"nm":"Trazado 1","mn":"ADBE Vector Shape - Group","hd":false},{"ty":"fl","c":{"a":0,"k":[1,1,1,1],"ix":4},"o":{"a":0,"k":15,"ix":5},"r":1,"bm":0,"nm":"Relleno 1","mn":"ADBE Vector Graphic - Fill","hd":false},{"ty":"tr","p":{"a":0,"k":[233.614,111.621],"ix":2},"a":{"a":0,"k":[0,0],"ix":1},"s":{"a":0,"k":[100,100],"ix":3},"r":{"a":0,"k":0,"ix":6},"o":{"a":0,"k":100,"ix":7},"sk":{"a":0,"k":0,"ix":4},"sa":{"a":0,"k":0,"ix":5},"nm":"Transformar"}],"nm":"Grupo 1","np":4,"cix":2,"bm":0,"ix":1,"mn":"ADBE Vector Group","hd":false},{"ty":"gr","it":[{"ind":0,"ty":"sh","ix":1,"ks":{"a":0,"k":{"i":[[0.838,-5.521],[0,0],[0,0],[5.192,1.937],[5.39,-1.292],[0,0],[3.784,-4.106]],"o":[[0,0],[0,0],[-3.225,-4.507],[-5.192,-1.937],[0,0],[-5.433,1.285],[-3.784,4.105]],"v":[[-232.831,14.321],[63.196,110.851],[232.831,-98.683],[219.915,-108.57],[203.679,-109.559],[-211.595,-8.717],[-225.738,-0.447]],"c":true},"ix":2},"nm":"Trazado 1","mn":"ADBE Vector Shape - Group","hd":false},{"ty":"fl","c":{"a":0,"k":[0.2901960784313726,0.5647058823529412,0.8862745098039215,1],"ix":4},"o":{"a":0,"k":100,"ix":5},"r":1,"bm":0,"nm":"Relleno 1","mn":"ADBE Vector Graphic - Fill","hd":false},{"ty":"tr","p":{"a":0,"k":[233.614,111.359],"ix":2},"a":{"a":0,"k":[0,0],"ix":1},"s":{"a":0,"k":[100,100],"ix":3},"r":{"a":0,"k":0,"ix":6},"o":{"a":0,"k":100,"ix":7},"sk":{"a":0,"k":0,"ix":4},"sa":{"a":0,"k":0,"ix":5},"nm":"Transformar"}],"nm":"Grupo 2","np":4,"cix":2,"bm":0,"ix":2,"mn":"ADBE Vector Group","hd":false},{"ty":"gr","it":[{"ind":0,"ty":"sh","ix":1,"ks":{"a":0,"k":{"i":[[0.838,-5.521],[0,0],[0,0],[5.192,1.937],[5.39,-1.292],[0,0],[3.784,-4.106]],"o":[[0,0],[0,0],[-3.227,-4.507],[-5.193,-1.938],[0,0],[-5.433,1.284],[-3.784,4.105]],"v":[[-232.895,1.864],[59.528,123.042],[232.895,-111.399],[219.98,-121.284],[203.744,-122.275],[-211.659,-21.175],[-225.802,-12.905]],"c":true},"ix":2},"nm":"Trazado 1","mn":"ADBE Vector Shape - Group","hd":false},{"ty":"fl","c":{"a":0,"k":[0.2901960784313726,0.5647058823529412,0.8862745098039215,1],"ix":4},"o":{"a":0,"k":100,"ix":5},"r":1,"bm":0,"nm":"Relleno 1","mn":"ADBE Vector Graphic - Fill","hd":false},{"ty":"tr","p":{"a":0,"k":[233.679,123.816],"ix":2},"a":{"a":0,"k":[0,0],"ix":1},"s":{"a":0,"k":[100,100],"ix":3},"r":{"a":0,"k":0,"ix":6},"o":{"a":0,"k":100,"ix":7},"sk":{"a":0,"k":0,"ix":4},"sa":{"a":0,"k":0,"ix":5},"nm":"Transformar"}],"nm":"Grupo 3","np":4,"cix":2,"bm":0,"ix":3,"mn":"ADBE Vector Group","hd":false},{"ty":"gr","it":[{"ind":0,"ty":"sh","ix":1,"ks":{"a":0,"k":{"i":[[-0.873,-3.448],[0,0],[-6.299,-3.826],[-7.159,1.747],[0,0],[-3.833,6.292],[1.71,7.166],[0,0],[2.066,2.891],[5.193,1.937],[5.391,-1.292],[0,0],[3.785,-4.105],[0.839,-5.52]],"o":[[0,0],[1.752,7.158],[6.299,3.825],[0,0],[7.153,-1.769],[3.833,-6.292],[0,0],[-0.869,-3.445],[-3.225,-4.507],[-5.193,-1.938],[0,0],[-5.434,1.283],[-3.784,4.105],[-0.533,3.517]],"v":[[-257.391,-34.432],[-212.987,148.268],[-200.413,165.422],[-179.395,168.668],[236.264,67.569],[253.415,54.986],[256.729,33.976],[212.326,-148.66],[207.884,-158.248],[194.968,-168.133],[178.733,-169.123],[-236.669,-68.024],[-250.813,-59.755],[-257.906,-44.985]],"c":true},"ix":2},"nm":"Trazado 1","mn":"ADBE Vector Shape - Group","hd":false},{"ty":"fl","c":{"a":0,"k":[0.2901960784313726,0.5647058823529412,0.8862745098039215,1],"ix":4},"o":{"a":0,"k":100,"ix":5},"r":1,"bm":0,"nm":"Relleno 1","mn":"ADBE Vector Graphic - Fill","hd":false},{"ty":"tr","p":{"a":0,"k":[258.689,170.666],"ix":2},"a":{"a":0,"k":[0,0],"ix":1},"s":{"a":0,"k":[100,100],"ix":3},"r":{"a":0,"k":0,"ix":6},"o":{"a":0,"k":100,"ix":7},"sk":{"a":0,"k":0,"ix":4},"sa":{"a":0,"k":0,"ix":5},"nm":"Transformar"}],"nm":"Grupo 4","np":4,"cix":2,"bm":0,"ix":4,"mn":"ADBE Vector Group","hd":false}],"ip":12.0000688541372,"op":93.0005336195634,"st":12.0000688541372,"bm":0},{"ddd":0,"ind":5,"ty":4,"nm":"Bubble/Inbox contornos 3","sr":1,"ks":{"o":{"a":0,"k":100,"ix":11},"r":{"a":1,"k":[{"i":{"x":[0.667],"y":[1]},"o":{"x":[0.333],"y":[0]},"t":87.001,"s":[0]},{"i":{"x":[0.182],"y":[1]},"o":{"x":[0.333],"y":[0]},"t":93.001,"s":[-3]},{"t":120.000729208272,"s":[45]}],"ix":10},"p":{"a":0,"k":[400,1030,0],"ix":2,"l":2},"a":{"a":0,"k":[378,868.5,0],"ix":1,"l":2},"s":{"a":1,"k":[{"i":{"x":[0.15,0.15,0.667],"y":[1,1,1]},"o":{"x":[0.333,0.333,0.333],"y":[0,0,0]},"t":94.001,"s":[100,100,100]},{"t":120.000729208272,"s":[0,0,100]}],"ix":6,"l":2}},"ao":0,"shapes":[{"ty":"gr","it":[{"ind":0,"ty":"sh","ix":1,"ks":{"a":0,"k":{"i":[[0,0],[66.705,-60.417],[9.039,-89.544],[-53.285,-72.53],[-88.151,-18.141],[-0.378,-0.29],[-0.219,-0.424],[0,0],[0,0],[-0.388,0.29],[-0.474,0.102],[-53.478,72.57],[9.029,89.694],[66.87,60.457],[90.146,-0.026]],"o":[[-89.999,0.159],[-66.705,60.418],[-9.039,89.544],[53.284,72.531],[0.466,0.103],[0.379,0.289],[0,0],[0,0],[0.232,-0.424],[0.389,-0.289],[88.345,-17.936],[53.479,-72.572],[-9.028,-89.694],[-66.868,-60.458],[0,0]],"v":[[0.065,-430.894],[-243.381,-336.787],[-361.053,-103.815],[-292.316,147.973],[-72.59,288.835],[-71.308,289.427],[-70.402,290.508],[0.065,427.582],[70.275,290.379],[71.217,289.298],[72.527,288.707],[292.879,148.083],[361.944,-104.031],[244.022,-337.323],[0.065,-431.216]],"c":true},"ix":2},"nm":"Trazado 1","mn":"ADBE Vector Shape - Group","hd":false},{"ind":1,"ty":"sh","ix":2,"ks":{"a":0,"k":{"i":[[0.589,0.013],[0.511,0.309],[0.274,0.534],[0,0],[54.097,73.925],[-9.367,91.124],[-68.005,61.373],[-91.604,0],[-68.005,-61.372],[-9.37,-91.123],[54.096,-73.925],[89.689,-18.638],[0,0],[0.502,-0.302]],"o":[[-0.596,0.006],[-0.512,-0.309],[0,0],[-89.688,-18.638],[-54.097,-73.925],[9.368,-91.123],[68.004,-61.372],[91.604,0],[68.004,61.373],[9.363,91.124],[-54.098,73.925],[0,0],[-0.258,0.534],[-0.501,0.309]],"v":[[0.065,437.878],[-1.629,437.421],[-2.831,436.14],[-75.293,294.563],[-298.668,150.769],[-368.157,-105.639],[-247.956,-342.547],[0.001,-437.891],[247.959,-342.547],[368.161,-105.639],[298.671,150.769],[75.294,294.563],[2.897,436.14],[1.734,437.421]],"c":true},"ix":2},"nm":"Trazado 2","mn":"ADBE Vector Shape - Group","hd":false},{"ty":"mm","mm":1,"nm":"Combinar trazados 1","mn":"ADBE Vector Filter - Merge","hd":false},{"ty":"fl","c":{"a":0,"k":[0.5647058823529412,0.07450980392156863,0.996078431372549,1],"ix":4},"o":{"a":0,"k":100,"ix":5},"r":1,"bm":0,"nm":"Relleno 1","mn":"ADBE Vector Graphic - Fill","hd":false},{"ty":"tr","p":{"a":0,"k":[377.774,438.141],"ix":2},"a":{"a":0,"k":[0,0],"ix":1},"s":{"a":0,"k":[100,100],"ix":3},"r":{"a":0,"k":0,"ix":6},"o":{"a":0,"k":100,"ix":7},"sk":{"a":0,"k":0,"ix":4},"sa":{"a":0,"k":0,"ix":5},"nm":"Transformar"}],"nm":"Grupo 1","np":6,"cix":2,"bm":0,"ix":1,"mn":"ADBE Vector Group","hd":false}],"ip":87.0105195833232,"op":121.010714670045,"st":74.0204653821697,"bm":0},{"ddd":0,"ind":6,"ty":4,"nm":"Bubble/Inbox contornos","sr":1,"ks":{"o":{"a":0,"k":100,"ix":11},"r":{"a":1,"k":[{"i":{"x":[0.667],"y":[1]},"o":{"x":[0.83],"y":[0]},"t":0,"s":[45]},{"i":{"x":[0.667],"y":[1]},"o":{"x":[0.333],"y":[0]},"t":41,"s":[-3]},{"t":50.0002868922384,"s":[0]}],"ix":10},"p":{"a":0,"k":[400,1030,0],"ix":2,"l":2},"a":{"a":0,"k":[378,868.5,0],"ix":1,"l":2},"s":{"a":1,"k":[{"i":{"x":[0.667,0.667,0.667],"y":[1,1,1]},"o":{"x":[0.896,0.896,0.333],"y":[0,0,0]},"t":0,"s":[0,0,100]},{"t":39.0002237759459,"s":[100,100,100]}],"ix":6,"l":2}},"ao":0,"shapes":[{"ty":"gr","it":[{"ind":0,"ty":"sh","ix":1,"ks":{"a":0,"k":{"i":[[0,0],[66.705,-60.417],[9.039,-89.544],[-53.285,-72.53],[-88.151,-18.141],[-0.378,-0.29],[-0.219,-0.424],[0,0],[0,0],[-0.388,0.29],[-0.474,0.102],[-53.478,72.57],[9.029,89.694],[66.87,60.457],[90.146,-0.026]],"o":[[-89.999,0.159],[-66.705,60.418],[-9.039,89.544],[53.284,72.531],[0.466,0.103],[0.379,0.289],[0,0],[0,0],[0.232,-0.424],[0.389,-0.289],[88.345,-17.936],[53.479,-72.572],[-9.028,-89.694],[-66.868,-60.458],[0,0]],"v":[[0.065,-430.894],[-243.381,-336.787],[-361.053,-103.815],[-292.316,147.973],[-72.59,288.835],[-71.308,289.427],[-70.402,290.508],[0.065,427.582],[70.275,290.379],[71.217,289.298],[72.527,288.707],[292.879,148.083],[361.944,-104.031],[244.022,-337.323],[0.065,-431.216]],"c":true},"ix":2},"nm":"Trazado 1","mn":"ADBE Vector Shape - Group","hd":false},{"ind":1,"ty":"sh","ix":2,"ks":{"a":0,"k":{"i":[[0.589,0.013],[0.511,0.309],[0.274,0.534],[0,0],[54.097,73.925],[-9.367,91.124],[-68.005,61.373],[-91.604,0],[-68.005,-61.372],[-9.37,-91.123],[54.096,-73.925],[89.689,-18.638],[0,0],[0.502,-0.302]],"o":[[-0.596,0.006],[-0.512,-0.309],[0,0],[-89.688,-18.638],[-54.097,-73.925],[9.368,-91.123],[68.004,-61.372],[91.604,0],[68.004,61.373],[9.363,91.124],[-54.098,73.925],[0,0],[-0.258,0.534],[-0.501,0.309]],"v":[[0.065,437.878],[-1.629,437.421],[-2.831,436.14],[-75.293,294.563],[-298.668,150.769],[-368.157,-105.639],[-247.956,-342.547],[0.001,-437.891],[247.959,-342.547],[368.161,-105.639],[298.671,150.769],[75.294,294.563],[2.897,436.14],[1.734,437.421]],"c":true},"ix":2},"nm":"Trazado 2","mn":"ADBE Vector Shape - Group","hd":false},{"ty":"mm","mm":1,"nm":"Combinar trazados 1","mn":"ADBE Vector Filter - Merge","hd":false},{"ty":"fl","c":{"a":0,"k":[0.5647058823529412,0.07450980392156863,0.996078431372549,1],"ix":4},"o":{"a":0,"k":100,"ix":5},"r":1,"bm":0,"nm":"Relleno 1","mn":"ADBE Vector Graphic - Fill","hd":false},{"ty":"tr","p":{"a":0,"k":[377.774,438.141],"ix":2},"a":{"a":0,"k":[0,0],"ix":1},"s":{"a":0,"k":[100,100],"ix":3},"r":{"a":0,"k":0,"ix":6},"o":{"a":0,"k":100,"ix":7},"sk":{"a":0,"k":0,"ix":4},"sa":{"a":0,"k":0,"ix":5},"nm":"Transformar"}],"nm":"Grupo 1","np":6,"cix":2,"bm":0,"ix":1,"mn":"ADBE Vector Group","hd":false}],"ip":0,"op":87.0004991924948,"st":0,"bm":0}],"markers":[]}